db/__init__.py
db/_version.py
db/celery.py
db/settings.py
db/urls.py
db/wsgi.py
db/api/__init__.py
db/api/drf_spectacular_hooks.py
db/api/filters.py
db/api/pagination.py
db/api/parsers.py
db/api/perms.py
db/api/renderers.py
db/api/serializers.py
db/api/tests.py
db/api/urls.py
db/api/views.py
db/base/__init__.py
db/base/admin.py
db/base/apps.py
db/base/context_processors.py
db/base/forms.py
db/base/helpers.py
db/base/models.py
db/base/signals.py
db/base/structured_data.py
db/base/tasks.py
db/base/tests.py
db/base/urls.py
db/base/utils.py
db/base/views.py
db/base/management/__init__.py
db/base/management/commands/__init__.py
db/base/management/commands/initialize.py
db/base/management/commands/update_all_tle.py
db/base/migrations/0001_initial.py
db/base/migrations/0001_squashed_0009_auto_20180103_1931.py
db/base/migrations/0002_auto_20150908_2054.py
db/base/migrations/0002_demoddata_is_decoded.py
db/base/migrations/0003_auto_20160504_2104.py
db/base/migrations/0003_satellite_tle_source.py
db/base/migrations/0004_auto_20170302_1641.py
db/base/migrations/0004_auto_20181215_1130.py
db/base/migrations/0005_demoddata_observer.py
db/base/migrations/0005_satellite_decayed.py
db/base/migrations/0006_auto_20170323_1715.py
db/base/migrations/0006_auto_20190121_1320.py
db/base/migrations/0007_satellite_status.py
db/base/migrations/0007_transmitter_rename.py
db/base/migrations/0008_satellite_description.py
db/base/migrations/0008_transmitter_model_change.py
db/base/migrations/0009_auto_20180103_1931.py
db/base/migrations/0009_auto_20190420_2306.py
db/base/migrations/0010_auto_20190421_0143.py
db/base/migrations/0011_transmitterentry_service.py
db/base/migrations/0012_auto_20191108_1840.py
db/base/migrations/0013_auto_20191108_1842.py
db/base/migrations/0014_increase_char_limit_on_mode_model.py
db/base/migrations/0015_satellite_dashboard_url.py
db/base/migrations/0016_increase_mode_name_char_limit.py
db/base/migrations/0017_exported_frameset.py
db/base/migrations/0018_artifact.py
satnogs_db-1.38.dist-info/LICENSE
satnogs_db-1.38.dist-info/METADATA
satnogs_db-1.38.dist-info/WHEEL
satnogs_db-1.38.dist-info/top_level.txt
satnogs_db-1.38.dist-info/RECORD
