Metadata-Version: 2.1
Name: satnogs-db
Version: 1.38
Summary: SatNOGS DB
Home-page: https://gitlab.com/librespacefoundation/satnogs/satnogs-db
Author: SatNOGS project
Author-email: dev@satnogs.org
License: AGPLv3
Platform: UNKNOWN
Classifier: Development Status :: 4 - Beta
Classifier: Environment :: Web Environment
Classifier: Framework :: Django
Classifier: Intended Audience :: Telecommunications Industry
Classifier: Intended Audience :: Science/Research
Classifier: License :: OSI Approved :: GNU Affero General Public License v3
Classifier: Operating System :: POSIX :: Linux
Classifier: Programming Language :: Python
Classifier: Programming Language :: Python :: 3
Classifier: Topic :: Communications :: Ham Radio
Classifier: Topic :: Internet :: WWW/HTTP
Classifier: Topic :: Internet :: WWW/HTTP :: Dynamic Content
License-File: LICENSE
Requires-Dist: Django (~=3.2.0)
Requires-Dist: django-shortuuidfield (~=0.1.0)
Requires-Dist: django-jsonfield (~=1.4.0)
Requires-Dist: celery (~=5.0.0)
Requires-Dist: mysqlclient (~=2.0.0)
Requires-Dist: django-redis-cache (~=3.0.0)
Requires-Dist: sentry-sdk (~=1.1.0)
Requires-Dist: python-decouple (~=3.4.0)
Requires-Dist: dj-database-url (~=0.5.0)
Requires-Dist: pytz
Requires-Dist: Unipath (~=1.1)
Requires-Dist: python-dotenv (~=0.17.0)
Requires-Dist: django-csp (~=3.7.0)
Requires-Dist: django-cors-headers (~=3.10.0)
Requires-Dist: django-allauth (~=0.44.0)
Requires-Dist: django-avatar (~=5.0.0)
Requires-Dist: django-crispy-forms (~=1.11.0)
Requires-Dist: python-jose[cryptography] (~=3.2.0)
Requires-Dist: social-auth-app-django (~=4.0.0)
Requires-Dist: django-compressor (~=2.4.0)
Requires-Dist: djangorestframework (~=3.12.0)
Requires-Dist: drf-spectacular (~=0.16.0)
Requires-Dist: Markdown (~=3.3.0)
Requires-Dist: django-filter (~=2.4.0)
Requires-Dist: sgp4 (~=2.19.0)
Requires-Dist: satellitetle (~=0.11.0)
Requires-Dist: influxdb (~=5.3.0)
Requires-Dist: django-widget-tweaks (~=1.4.8)
Requires-Dist: django-bootstrap-modal-forms (~=2.2.0)
Requires-Dist: django-fontawesome-5
Requires-Dist: satnogs-decoders (~=1.0)
Requires-Dist: simplejson (~=3.17.0)
Requires-Dist: uritemplate (~=3.0.0)
Requires-Dist: PyYAML (~=5.4.0)
Requires-Dist: h5py (~=3.2.0)
Requires-Dist: PyLD (~=2.0.3)
Requires-Dist: pyzmq (~=22.0.0)
Requires-Dist: nanoid (~=2.0.0)
Requires-Dist: urllib3 (~=1.26)
Requires-Dist: requests (~=2.25.0)
Requires-Dist: django-countries (~=7.2.0)
Requires-Dist: django-debug-toolbar (~=3.2.0)
Requires-Dist: eventlet (==0.29.1)
Requires-Dist: gunicorn[eventlet] (==19.9.0)
Provides-Extra: dev
Requires-Dist: pytest-celery ; extra == 'dev'
Requires-Dist: pytest-cov (~=2.12.0) ; extra == 'dev'
Requires-Dist: pytest-django (~=4.2.0) ; extra == 'dev'
Requires-Dist: pytest-forked (~=1.3.0) ; extra == 'dev'
Requires-Dist: pytest-xdist (~=2.2.0) ; extra == 'dev'
Requires-Dist: mock (~=4.0.0) ; extra == 'dev'
Requires-Dist: Faker (~=8.1.0) ; extra == 'dev'
Requires-Dist: factory-boy (~=3.2.0) ; extra == 'dev'
Requires-Dist: pur (~=5.4.0) ; extra == 'dev'
Requires-Dist: docopts (~=0.6.0) ; extra == 'dev'
Requires-Dist: tox (~=3.23.0) ; extra == 'dev'
